altf1be_google_analytics_helpers/__init__.py
altf1be_google_analytics_helpers/altf1be_google_analytics_helpers.py
altf1be_google_analytics_helpers-1.0.0.dist-info/LICENSE
altf1be_google_analytics_helpers-1.0.0.dist-info/METADATA
altf1be_google_analytics_helpers-1.0.0.dist-info/WHEEL
altf1be_google_analytics_helpers-1.0.0.dist-info/top_level.txt
altf1be_google_analytics_helpers-1.0.0.dist-info/RECORD
