Metadata-Version: 2.1
Name: altf1be-google-analytics-helpers
Version: 1.0.0
Summary: Google Analytics helpers facilitating the setting of the categories, actions, labels, User Id and User Agents built by www.alt-f1.be
Home-page: https://bitbucket.org/altf1be/altf1be_google_analytics_helpers
Author: Abdelkrim Boujraf
Author-email: abo+altf1be_google_analytics_helpers_pkg@alt-f1.be
License: EUPL-1.2
Project-URL: Bug Reports, https://bitbucket.org/altf1be/altf1be_google_analytics_helpers/admin/issues
Project-URL: Company behind the library, http://www.alt-f1.be
Project-URL: Source, https://bitbucket.org/altf1be/altf1be_google_analytics_helpers
Keywords: library,altf1be_google_analytics_helpers,alt-f1.be,helpers-library,python3,pypi-package
Platform: UNKNOWN
Classifier: Development Status :: 5 - Production/Stable
Classifier: Intended Audience :: Developers
Classifier: License :: OSI Approved :: European Union Public Licence 1.2 (EUPL 1.2)
Classifier: Operating System :: OS Independent
Classifier: Programming Language :: Python :: 3.8
Classifier: Topic :: Software Development :: Libraries :: Python Modules
Requires-Python: >=3.8
Requires-Dist: requests (==2.25.0)
Requires-Dist: python-dotenv (==0.15.0)
